Metadata-Version: 2.1
Name: algo-fun-anagram
Version: 0.1.0
Summary: Check if 2 strings are anagram or not
Home-page: https://gitlab.com/ChristopheLagaillarde/algo_fun_anagram
Author: Christophe Lagaillarde
Author-email: chrislag94@gmail.com
License: MIT
License-File: LICENSE
